wordstreamer/__init__.py
wordstreamer/core.py
wordstreamer/functional.py
wordstreamer/internal_types.py
wordstreamer/py.typed
wordstreamer/startkit.py
wordstreamer/stream_utils.py
wordstreamer/utils.py
wordstreamer-0.1.3.dist-info/LICENSE
wordstreamer-0.1.3.dist-info/METADATA
wordstreamer-0.1.3.dist-info/WHEEL
wordstreamer-0.1.3.dist-info/RECORD
