Metadata-Version: 2.1
Name: wordstreamer
Version: 0.1.3
Summary: 
Home-page: https://github.com/evtn/wordstreamer
License: MIT
Author: Dmitry Gritsenko
Author-email: wordstreamer@evtn.me
Requires-Python: >=3.7,<4.0
Classifier: License :: OSI Approved :: MIT License
Classifier: Programming Language :: Python :: 3
Classifier: Programming Language :: Python :: 3.7
Classifier: Programming Language :: Python :: 3.8
Classifier: Programming Language :: Python :: 3.9
Classifier: Programming Language :: Python :: 3.10
Classifier: Programming Language :: Python :: 3.11
Classifier: Programming Language :: Python :: 3.12
Requires-Dist: typing-extensions (>=4.7,<5.0)
Project-URL: Repository, https://github.com/evtn/wordstreamer
